Iris_heureka_code/Event.py
Iris_heureka_code/Handler.py
Iris_heureka_code/RecursiveHandler.py
Iris_heureka_code/StaticHandler.py
Iris_heureka_code/TypeEvent.py
Iris_heureka_code/__init__.py
Iris_heureka_code-1.2.0.dist-info/LICENSE.txt
Iris_heureka_code-1.2.0.dist-info/METADATA
Iris_heureka_code-1.2.0.dist-info/WHEEL
Iris_heureka_code-1.2.0.dist-info/top_level.txt
Iris_heureka_code-1.2.0.dist-info/RECORD
