Metadata-Version: 2.1
Name: Iris-heureka-code
Version: 1.2.0
Summary: Eventbasierte Kommunikation
Home-page: https://github.com/heureka-code/Iris-heureka-code
Author: heureka-code
License: MIT
Download-URL: https://github.com/heureka-code/Iris-heureka-code/archive/refs/tags/1.2.0.tar.gz
Platform: UNKNOWN
License-File: LICENSE.txt
